D_FF.v
module D_FF (output q,
input d,
input clk,
input reset);
reg q;
always @(posedge reset or negedge clk)
if(reset)
q <= 1'b0;
else
q<=d;
endmodule

T_FF.v
`include "D_FF.v"
module T_FF (
    output q,
    input clk,
    input reset
);
wire d;

D_FF dff0(q, d, clk, reset);
not n1(d, q);

endmodule

rip_counter.v
`include "T_FF.v"
module rip_counter(
    output [3:0] q,
    input clk,
    input reset
);
T_FF tff0(q[0],  clk, reset);
T_FF tff1(q[1], q[0], reset);
T_FF tff2(q[2], q[1], reset);
T_FF tff3(q[3], q[2], reset);

endmodule

counter_tb.v
`timescale 1s/100ms
`include "rip_counter.v"
module counter_tb();
reg clk;
reg reset;
wire [3:0] q;
rip_counter ir(q, clk, reset);
initial
 clk = 1'b0;
always 
 #5 clk = ~clk;
 initial
begin
  reset=1'b1;
  #15 reset = 1'b0;
  #180 reset = 1'b1;
  #10 reset = 1'b0;
  #20 $finish;
end
initial 
begin
$monitor ($time, "  Output q = %d , clk=%d , reset=%d" , q , clk, reset );
$dumpfile("counter_tb.vcd");
$dumpvars(0, counter_tb);
clk=0; reset=0; #5;
clk=0; reset=1; #100;
clk=1; reset=0; #105;
clk=0; reset=1; #20;
clk=0; reset=0; #5;
clk=0; reset=1; #10;
clk=1; reset=0; #15;
clk=0; reset=1; #20;
$finish;
end
endmodule

counter_tb.vcd
$date
	Mon Jun 15 23:04:10 2020
$end
$version
	Icarus Verilog
$end
$timescale
	100ms
$end
$scope module counter_tb $end
$var wire 4 ! q [3:0] $end
$var reg 1 " clk $end
$var reg 1 # reset $end
$scope module ir $end
$var wire 1 " clk $end
$var wire 1 # reset $end
$var wire 4 $ q [3:0] $end
$scope module tff0 $end
$var wire 1 " clk $end
$var wire 1 % d $end
$var wire 1 # reset $end
$var wire 1 & q $end
$scope module dff0 $end
$var wire 1 " clk $end
$var wire 1 % d $end
$var wire 1 # reset $end
$var reg 1 & q $end
$upscope $end
$upscope $end
$scope module tff1 $end
$var wire 1 ' clk $end
$var wire 1 ( d $end
$var wire 1 # reset $end
$var wire 1 ) q $end
$scope module dff0 $end
$var wire 1 ' clk $end
$var wire 1 ( d $end
$var wire 1 # reset $end
$var reg 1 ) q $end
$upscope $end
$upscope $end
$scope module tff2 $end
$var wire 1 * clk $end
$var wire 1 + d $end
$var wire 1 # reset $end
$var wire 1 , q $end
$scope module dff0 $end
$var wire 1 * clk $end
$var wire 1 + d $end
$var wire 1 # reset $end
$var reg 1 , q $end
$upscope $end
$upscope $end
$scope module tff3 $end
$var wire 1 - clk $end
$var wire 1 . d $end
$var wire 1 # reset $end
$var wire 1 / q $end
$scope module dff0 $end
$var wire 1 - clk $end
$var wire 1 . d $end
$var wire 1 # reset $end
$var reg 1 / q $end
$upscope $end
$upscope $end
$upscope $end
$upscope $end
$enddefinitions $end
#0
$dumpvars
x/
x.
x-
x,
x+
x*
x)
x(
x'
x&
x%
bx $
0#
0"
bx !
$end
#50
1(
0*
1+
0-
1.
1%
0'
0)
0,
0/
b0 !
b0 $
0&
1#
0"
#100
1"
#150
0%
1'
b1 !
b1 $
1&
0"
0#
#200
1"
#250
0(
1*
1)
1%
0'
b10 !
b10 $
0&
0"
#300
1"
#350
0%
1'
b11 !
b11 $
1&
0"
#400
1"
#450
0+
1-
1,
1(
0*
0)
1%
0'
b100 !
b100 $
0&
0"
#500
1"
#550
0%
1'
b101 !
b101 $
1&
0"
#600
1"
#650
0(
1*
1)
1%
0'
b110 !
b110 $
0&
0"
#700
1"
#750
0%
1'
b111 !
b111 $
1&
0"
#800
1"
#850
0.
1/
1+
0-
0,
1(
0*
0)
1%
0'
b1000 !
b1000 $
0&
0"
#900
1"
#950
0%
1'
b1001 !
b1001 $
1&
0"
#1000
1"
#1050
0(
1*
1)
1%
0'
b1010 !
b1010 $
0&
0"
#1100
1"
#1150
0%
1'
b1011 !
b1011 $
1&
0"
#1200
1"
#1250
0+
1-
1,
1(
0*
0)
1%
0'
b1100 !
b1100 $
0&
0"
#1300
1"
#1350
0%
1'
b1101 !
b1101 $
1&
0"
#1400
1"
#1450
0(
1*
1)
1%
0'
b1110 !
b1110 $
0&
0"
#1500
1"
#1550
0%
1'
b1111 !
b1111 $
1&
0"
#1600
1"
#1650
1.
0/
1+
0-
0,
1(
0*
0)
1%
0'
b0 !
b0 $
0&
0"
#1700
1"
#1750
0%
1'
b1 !
b1 $
1&
0"
#1800
1"
#1850
0(
1*
1)
1%
0'
b10 !
b10 $
0&
0"
#1900
1"
#1950
1(
0*
b0 !
b0 $
0)
0"
1#
#2000
1"
#2050
0%
1'
b1 !
b1 $
1&
0"
0#
#2100
1%
0'
b0 !
b0 $
0&
1"
1#
